txtrader_client/__init__.py
txtrader_client/__main__.py
txtrader_client/cli.py
txtrader_client/client.py
txtrader_client/defaults.py
txtrader_client/version.py
txtrader_client-1.5.4.data/data/LICENSE
txtrader_client-1.5.4.data/data/requirements.txt
txtrader_client-1.5.4.dist-info/LICENSE
txtrader_client-1.5.4.dist-info/METADATA
txtrader_client-1.5.4.dist-info/WHEEL
txtrader_client-1.5.4.dist-info/entry_points.txt
txtrader_client-1.5.4.dist-info/top_level.txt
txtrader_client-1.5.4.dist-info/RECORD
