Metadata-Version: 2.1
Name: txtrader-client
Version: 1.5.4
Summary: TxTrader Securities Trading API Client
Home-page: https://github.com/rstms/txtrader_client/
Author: Matt Krueger
Author-email: mkrueger@rstms.net
License: MIT
Keywords: trading api txtrader twisted
Platform: UNKNOWN
Classifier: Programming Language :: Python :: 3
Classifier: License :: OSI Approved :: MIT License
Classifier: Operating System :: OS Independent
Classifier: Environment :: Console
Requires-Dist: requests (==2.24.0)
Requires-Dist: click (==7.1.2)
